wumbo/__init__.py
wumbo-1.0.0.dist-info/METADATA
wumbo-1.0.0.dist-info/WHEEL
wumbo-1.0.0.dist-info/top_level.txt
wumbo-1.0.0.dist-info/RECORD
