Metadata-Version: 2.1
Name: wumbo
Version: 1.0.0
Summary: Wumbology, the study of Wumbo
Home-page: UNKNOWN
Author: Aaron Graubert, but mostly Shankara Anand
Author-email: totallyfakeemail@gmail.com
License: UNKNOWN
Platform: UNKNOWN
Classifier: Programming Language :: Python :: 2
Classifier: Programming Language :: Python :: 3
